[
    {
        "question": "…………… climate is the healthiest climate.",
        "options": [
            "Tropical",
            "Temperate",
            "Coastal"
        ],
        "answer":2 
    },
    {
        "question": "The negative Trend in population in India is shown from ……………",
        "options": [
            "1999",
            "2001",
            "2011"
        ],
        "answer":2
    },
    {
        "question": "It is the one of the most important resources for any country.",
        "options": [
            "Money",
            "Population",
            "Electricity",
            "Natural Resources"
        ],
        "answer":2 
    },
    {
        "question": "…………… and climate play an important role in the distribution of population",
        "options": [
            "Physiography",
            "Temperature",
            "Rainfall"
        ],
        "answer":1
    },
    {
        "question": "In Brazilian population the number of …………… population is increasing.",
        "options": [
            "Old",
            "Young",
            "Children"
        ],
        "answer":1 
    },
    {
        "question": "The density of population is around …………… persons per sq. km. in Brazil.",
        "options": [
            "100",
            "23",
            "75"
        ],
        "answer":2 
    },
    {
        "question": "India is the …………… populous country in the world.",
        "options": [
            "Second",
            "Fifth",
            "Third"
        ],
        "answer":1 
    },
    {
        "question": "States in India having highest population density",
        "options": [
            "Punjab",
            "Bihar",
            "Arunachal pradesh",
            "Uttar Pradesh"
        ],
        "answer":3
    },
    {
        "question": "Arrange the following states of India in descending order of their population.",
        "options": [
            "Himachal Pradesh, Uttar Pradesh, Arunachal Pradesh, Madhya Pradesh, Andhra Pradesh",
            "Uttar Pradesh, Arunachal Pradesh, Madhya Pradesh, Andhra Pradesh, Himachal Pradesh",
            "Uttar Pradesh, Arunachal Pradesh, Andhra Pradesh, Himachal Pradesh, Madhya Pradesh",
            "Uttar Pradesh, Andhra Pradesh, Madhya Pradesh, Himachal Pradesh, Arunachal Pradesh"
        ],
        "answer":4 
    },
    {
        "question": "Name the highly dense state in India.",
        "options": [
            "Name the highly dense state in India.",
            "Himachal Pradesh",
            "Mizoram"
        ],
        "answer":1 
    },
    {
        "question": "Sex ratio means number of males against …………… females.",
        "options": [
            "1000",
            "500",
            "100"
        ],
        "answer":1 
    },
    {
        "question": "Brazil is the …………… longest populated country in the world.",
        "options": [
            "Second",
            "Third",
            "Fifth"
        ],
        "answer":3 
    },
    {
        "question": "The distribution of population is very ............... in Brazil.",
        "options": [
            "even",
            "more",
            "moderate",
            "extreme"
        ],
        "answer":3 
    },
    {
        "question": "As per 2011 Census, India's population was around ............... crores.",
        "options": [
            "111",
            "120",
            "121",
            "122"
        ],
        "answer":3 
    },
    {
        "question": "…………… is an important resource of any country.",
        "options": [
            "Industries",
            "Population",
            "Agriculture"
        ],
        "answer":2 
    },
    {
        "question": "The growth rate is …………… in Brail’s population.",
        "options": [
            "Increase",
            "Declining",
            "Declining"
        ],
        "answer":2 
    },
    {
        "question": "Brazil occupies ............... of world's total land.",
        "options": [
            "Espirito santo",
            "Espirito santo",
            "Para",
            "Amapa"
        ],
        "answer":1 
    },
    {
        "question": "Mountainous region, dry deserts, …………… areas have sparse population",
        "options": [
            "Coastal",
            "Plateau",
            "Dense forests"
        ],
        "answer":3 
    },
    {
        "question": "Arrange the states of Brazil in ascending order of their population.",
        "options": [
            "Amazonas, Rio de Janeiro, Alagoas, Sao Paulo, Parana",
            "Amazonas, Alagoas, Parana, Sao Paulo, Rio de Janeiro",
            "Amazonas, Sao Paulo, Rio de Janeiro, Alagoas, Parana",
            "Sao Paulo, Rio de Janeiro, Alagoas, Parana, Amazonas"
        ],
        "answer":2 
    },
    {
        "question": "Identify the growing Trend of population in Brazil",
        "options": [
            "Increasing",
            "Decreasing",
            "Stagnant"
        ],
        "answer":2 
    },
    {
        "question": "Distribution of population can be best shown by …………… method of map.",
        "options": [
            "Dot",
            "Line",
            "Colour"
        ],
        "answer":1 
    },
    {
        "question": "The sex ratio of Brazil has been ............... 1000 since decades.",
        "options": [
            "more than",
            "less than",
            "equal to",
            "around"
        ],
        "answer":1 
    },
    {
        "question": "‘Save Girl, Teach Girl’ is a slogan for maintaining ……………",
        "options": [
            "Literacy rate",
            "Sex-ratio",
            "Growth rate"
        ],
        "answer":2 
    },
    {
        "question": "North India plain is …………… populated area.",
        "options": [
            "Sparsely",
            "Highl",
            "Moderately"
        ],
        "answer":2 
    },
    {
        "question": "Brazil is the most populated country in the …………… continent.",
        "options": [
            "North American",
            "European",
            "South American",
            "Australian"
        ],
        "answer":4 
    },
    {
        "question": "The highest son-ratio is in …………… state in India",
        "options": [
            "Goa",
            "Punjab",
            "Kerala"
        ],
        "answer":3 
    },
    {
        "question": "The average density of population in India is …………… persons per sq. km.",
        "options": [
            "250",
            "300",
            "382"
        ],
        "answer":3 
    },
    {
        "question": "There has been a slight increase in the sex ratio in India after ...............",
        "options": [
            "1971",
            "1981",
            "1947",
            "1991"
        ],
        "answer":4 
    },
    {
        "question": "With a population of around 19 crores, (as per 2010 Census) Brazil ranks ............... in the world.",
        "options": [
            "5th",
            "4th",
            "6th",
            "2nd"
        ],
        "answer":1 
    }
]