[
    {
        "question": "The ............... of development available to people in developed states are not possible for people in backwardstates.",
        "options": [
            "Favourable",
            "Misfortune",
            "Opportunities",
            "Freedom"
        ],
        "answer": 3
    },
    {
        "question": "Bhindranwale's followers captured the ............... and built a barricade of sand bags over there.",
        "options": [
            "Jallianwala Bagh",
            "Akal Takht",
            "Siddhi Vinayak Temple",
            "Golden Temple"
        ],
        "answer": 4
    },
    {
        "question": "............... is a serious threat to the unity of our country.",
        "options": [
            "Imperialism",
            "Racism",
            "Communalism",
            "Casteism"
        ],
        "answer": 3
    },
    {
        "question": "The main task of getting the terrorist out of the Golden Temple was entrusted to Major General ............... .",
        "options": [
            "Kuldeep Singh Brar",
            "Manjeet Singh",
            "Pandit Jawaharlal Nehru",
            "Laldenga"
        ],
        "answer": 1
    },
    {
        "question": "When the situation calmed down in 1972, the Mizo Majority area was given the status of a ............... .",
        "options": [
            "Union Territory",
            "State",
            "District",
            "Taluka"
        ],
        "answer": 1
    },
    {
        "question": "Due to these development, ............... rule was imposed in Punjab in 1983.",
        "options": [
            "President's",
            "Prime Minister",
            "Chief Minister",
            "Military's"
        ],
        "answer": 1
    },
    {
        "question": "International Borders of India touch each of the states to ............... extents.",
        "options": [
            "Varying",
            "Changing",
            "Unsteady",
            "Waffing"
        ],
        "answer": 1
    },
    {
        "question": "The ............... tribe in North-East India is known as a martial tribe.",
        "options": [
            "Mizo",
            "Adivasis",
            "Arun",
            "Naga"
        ],
        "answer": 4
    },
    {
        "question": "In 1959, the territory of ............... experienced severe drought",
        "options": [
            "Arunachal Pradesh",
            "Mizoram",
            "Naga Land",
            "Darjeeling"
        ],
        "answer": 2
    },
    {
        "question": "The love for one's province turns ............... due to this kind of an excessive regional pride.",
        "options": [
            "Nasty",
            "Gloomy",
            "Abnormal",
            "Morbid"
        ],
        "answer": 4
    },
    {
        "question": "These states are different with respect to ethnicity, language and cultural ............... .",
        "options": [
            "Variety",
            "Diversity",
            "Difference",
            "Similarity"
        ],
        "answer": 2
    },
    {
        "question": "Regionalism can ............... developed as well as undeveloped states.",
        "options": [
            "Affect",
            "Inspire",
            "Influence",
            "Imitate"
        ],
        "answer": 1
    },
    {
        "question": "Laldenga became the ............... of the state.",
        "options": [
            "Chief Minister",
            "Prime Minister",
            "Chancellor",
            "Chief Cabinet Head"
        ],
        "answer": 1
    },
    {
        "question": "Regionalism means having ............... pride about one's region.",
        "options": [
            "Overdone",
            "Superabundant",
            "Excessive",
            "Exorbitant"
        ],
        "answer": 3
    },
    {
        "question": "The first Prime Minister of Independent India took the lead in bringing the ............... living in these areas intothe mainstream of the country.",
        "options": [
            "Nomads",
            "Tribes",
            "Race",
            "Kin"
        ],
        "answer": 2
    },
    {
        "question": "Prime Minister Indira Gandhi handled the situation firmly and suppressed the ............... .",
        "options": [
            "Revolt",
            "Rebellion",
            "Uprising",
            "Insurgence"
        ],
        "answer": 2
    },
    {
        "question": "............... is the base of communalism.",
        "options": [
            "Imperialism",
            "Racism",
            "Fanaticism",
            "None of the above"
        ],
        "answer": 3
    },
    {
        "question": "While taking charge, they asked for a larger share of river waters for Punjab, 'holy city' status for ...............,etc. along with their old demands",
        "options": [
            "Amritsar",
            "Chandigarh",
            "Ludhiana",
            "Jalandhar"
        ],
        "answer": 1
    },
    {
        "question": "People of different ............... have happily lived together since many centuries.",
        "options": [
            "Religions",
            "Languages",
            "Culture",
            "Both 1 & 2"
        ],
        "answer": 1
    },
    {
        "question": "The tribes in north - east India have an ............... history.",
        "options": [
            "Ancient",
            "Modern",
            "Medieval",
            "None of the above"
        ],
        "answer": 1
    },
    {
        "question": "Akali dal came to power in Punjab in ............... .",
        "options": [
            "1973",
            "1947",
            "1983",
            "1977"
        ],
        "answer": 4
    },
    {
        "question": "In order to maintain their influence, the Naxalites established an ............... called people's Liberation GuerillaArmy (PLGA).",
        "options": [
            "Administration",
            "Organisation",
            "Group",
            "Party"
        ],
        "answer": 2
    },
    {
        "question": "In ..............., the movement for 'Independence Khalistan' took root in Punjab.",
        "options": [
            "1982",
            "1980",
            "1977",
            "1973"
        ],
        "answer": 2
    },
    {
        "question": "A military expedition taken up with a particular objective is called an ............... .",
        "options": [
            "Action",
            "Movement",
            "Operation",
            "Procedure"
        ],
        "answer": 3
    },
    {
        "question": "During that period, the ............... of the Akali Dal was Sant Harcharan Singh Longowal.",
        "options": [
            "Agent",
            "Pilot",
            "Leader",
            "Captain"
        ],
        "answer": 3
    },
    {
        "question": "Some people begin to think of economic and social question also in the ............... of their own religion.",
        "options": [
            "Core",
            "Foundation",
            "Framework",
            "Scheme"
        ],
        "answer": 3
    },
    {
        "question": "On the morning of, 3rd June 1984, the ............... 'Operation Blue Star, started.",
        "options": [
            "Purpose",
            "Mission",
            "Task",
            "Assignment"
        ],
        "answer": 2
    },
    {
        "question": "The evil of regionalism can be tackled by reducing the ............... in development.",
        "options": [
            "Inequality",
            "Imbalance",
            "Shortcoming",
            "Both 1 & 2"
        ],
        "answer": 2
    },
    {
        "question": "Special provisions have been made with respect to these areas in the ............... schedule of the Indianconstitution.",
        "options": [
            "V",
            "IV",
            "VI",
            "VII"
        ],
        "answer": 3
    },
    {
        "question": "The Naxalites started a ............... system by rejecting the democratic system.",
        "options": [
            "Parallel",
            "Lateral",
            "Aligned",
            "Both 1 & 2"
        ],
        "answer": 1
    },
    {
        "question": "Akali Dal was the major ............... party in Punjab.",
        "options": [
            "Political",
            "Bureaucratic",
            "Legislative",
            "Official"
        ],
        "answer": 1
    },
    {
        "question": "In 1954, ............... was created.",
        "options": [
            "FERA",
            "NEFA",
            "RERA",
            "ASEAN"
        ],
        "answer": 2
    },
    {
        "question": "If trust breaks, ............... unity receives a blow.",
        "options": [
            "Social",
            "Public",
            "Group",
            "Cordial"
        ],
        "answer": 1
    },
    {
        "question": "During this famine, Mizo leader ............... served the common people a lot.",
        "options": [
            "Indira Gandhi",
            "Rajiv Gandhi",
            "Laldenga",
            "Jawaharlal Nehru"
        ],
        "answer": 3
    },
    {
        "question": "Fanaticism makes the ............... of looking at events and people prejudiced.",
        "options": [
            "Outlook",
            "Perspective",
            "Mindset",
            "View Point"
        ],
        "answer": 2
    },
    {
        "question": "Bhindranwale was arrested in ..............., accused of the murder of Newspaper editor, Lala Jagatnarayan.",
        "options": [
            "1982",
            "1970",
            "1973",
            "1981"
        ],
        "answer": 4
    },
    {
        "question": "Compatriots following different religions are looked at as ............... .",
        "options": [
            "Enemies",
            "Friends",
            "Rivals",
            "None of the above."
        ],
        "answer": 1
    },
    {
        "question": "In ..............., skirmishes happened between local Nagas and the soldiers of the Assam Rifles.",
        "options": [
            "1947",
            "1958",
            "1966",
            "1955"
        ],
        "answer": 4
    },
    {
        "question": "In 1986, ............... were held for held for Assam Legislative Assembly and Prafullakumar Mohanto, of the AsomGanaparishad became the new Chief Minister.",
        "options": [
            "Elections",
            "Selections",
            "Combination",
            "Appointment"
        ],
        "answer": 1
    },
    {
        "question": "In 1961, Laldenga ............... an organisation called Mizo National Front (MNF).",
        "options": [
            "Proposed",
            "Rooted",
            "Settled",
            "Established"
        ],
        "answer": 4
    }
]